getscrambled/__init__.py
getscrambled/constants.py
getscrambled/decode.py
getscrambled/encode.py
getscrambled/exceptions.py
getscrambled/shared.py
getscrambled-1.0.0.dist-info/LICENSE
getscrambled-1.0.0.dist-info/METADATA
getscrambled-1.0.0.dist-info/WHEEL
getscrambled-1.0.0.dist-info/RECORD
