Metadata-Version: 2.1
Name: getscrambled
Version: 1.0.0
Summary: Protect unintended copy of your images by hiding the key in plain sight
Home-page: https://github.com/Starmania/getscrambled
License: CERN-OHL-P-2.0-1
Author: Starmania
Author-email: wycvhrt6vzscfpedxr@gmail.com
Requires-Python: >=3.9,<3.13
Classifier: License :: Other/Proprietary License
Classifier: Programming Language :: Python :: 3
Classifier: Programming Language :: Python :: 3.9
Classifier: Programming Language :: Python :: 3.10
Classifier: Programming Language :: Python :: 3.11
Requires-Dist: stegano (>=0.11.3,<0.12.0)
Project-URL: Repository, https://github.com/Starmania/getscrambled
